angus_sdk_python-0.0.10.dist-info/WHEEL
angus_sdk_python-0.0.10.dist-info/DESCRIPTION.rst
angus_sdk_python-0.0.10.dist-info/RECORD
angus_sdk_python-0.0.10.dist-info/top_level.txt
angus_sdk_python-0.0.10.dist-info/METADATA
angus_sdk_python-0.0.10.dist-info/metadata.json
angus/cloud.py
angus/__init__.py
angus/rest.py
angus/version.py
angus_sdk_python-0.0.10.data/scripts/angusme
