Metadata-Version: 2.0
Name: angus-sdk-python
Version: 0.0.10
Summary: Angus python SDK
Home-page: http://www.angus.ai/
Author: Aurélien Moreau
Author-email: aurelien.moreau@yienyien.net
License: Apache v2.0
Platform: UNKNOWN
Requires-Dist: requests (==2.5.3)
Requires-Dist: argparse (==1.2.1)
Requires-Dist: pytest (==2.6.4)
Requires-Dist: six
Requires-Dist: requests-futures
